{
  "required": true,
  "package": "com.mikitellurium.superflatbiomeextension.mixin",
  "compatibilityLevel": "JAVA_21",
  "mixins": [
    "ChunkNoiseSamplerAccessor",
    "DensityFunctionsAccessor",
    "DimensionOptionsRegistryHolderMixin",
    "GenerationShapeConfigAccessor",
    "JigsawStructureAccessor",
    "ServerChunkLoadingManagerMixin",
    "StructureAccessors$Jigsaw",
    "StructureAccessors$OceanMonumentBase",
    "StructureFixMix$OceanMonument",
    "StructureFixMix$WoodlandMansion",
    "SurfaceBuilderMixin"
  ],
  "injectors": {
    "defaultRequire": 1
  }
}